LICENSE.txt
MANIFEST.in
README.md
setup.cfg
setup.py
src/letsencrypt_gencsr/__init__.py
src/letsencrypt_gencsr/cli.py
src/letsencrypt_gencsr/crypto_addition_util.py
src/letsencrypt_gencsr/key_client.py
src/letsencrypt_gencsr.egg-info/PKG-INFO
src/letsencrypt_gencsr.egg-info/SOURCES.txt
src/letsencrypt_gencsr.egg-info/dependency_links.txt
src/letsencrypt_gencsr.egg-info/entry_points.txt
src/letsencrypt_gencsr.egg-info/namespace_packages.txt
src/letsencrypt_gencsr.egg-info/not-zip-safe
src/letsencrypt_gencsr.egg-info/requires.txt
src/letsencrypt_gencsr.egg-info/top_level.txt
src/letsencrypt_gencsr/cmd/__init__.py
src/letsencrypt_gencsr/cmd/gencsr.py
src/letsencrypt_gencsr/cmd/helpers.py
src/letsencrypt_gencsr/cmd/obtain_cert.py
src/letsencrypt_gencsr/cmd/run.py