Metadata-Version: 1.1
Name: letsencrypt-gencsr
Version: 0.2.0
Summary: Command line utility to generate a csr for letsencrypt from a preexisting key
Home-page: https://github.com/cbrand/letsencrypt_gencsr
Author: Christoph Brand
Author-email: christoph@brand.rest
License: UNKNOWN
Download-URL: https://github.com/cbrand/letsencrypt_gencsr/tarball/0.2.0
Keywords: network,letsencrypt,ssl
Platform: UNKNOWN
Classifier: Programming Language :: Python
Classifier: Development Status :: 3 - Alpha
Classifier: Programming Language :: Python :: 2 :: Only
Classifier: Programming Language :: Python :: 2.7
Classifier: Topic :: System :: Networking
